f3rm/__init__.py
f3rm/f3rm_config.py
f3rm/feature_datamanager.py
f3rm/feature_field.py
f3rm/model.py
f3rm/pca_colormap.py
f3rm/renderer.py
f3rm/features/__init__.py
f3rm/features/clip_extract.py
f3rm/features/dino_extract.py
f3rm/features/clip/README.md
f3rm/features/clip/__init__.py
f3rm/features/clip/bpe_simple_vocab_16e6.txt.gz
f3rm/features/clip/clip.py
f3rm/features/clip/interpolate.py
f3rm/features/clip/model.py
f3rm/features/clip/simple_tokenizer.py
f3rm/features/dino/__init__.py
f3rm/features/dino/dino_vit_extractor.py
f3rm/scripts/__init__.py
f3rm/scripts/demo_clip_features.py
f3rm/scripts/demo_extract_features.py
f3rm/scripts/download_datasets.py
f3rm/scripts/images/frame_1.png
f3rm/scripts/images/frame_2.png
f3rm/scripts/images/frame_3.png
f3rm_robot/README.md
f3rm_robot/__init__.py
f3rm_robot/args.py
f3rm_robot/collision.py
f3rm_robot/field_adapter.py
f3rm_robot/initial_proposals.py
f3rm_robot/load.py
f3rm_robot/optimize.py
f3rm_robot/task.py
f3rm_robot/utils.py
f3rm_robot/visualizer.py
f3rm_robot/assets/__init__.py
f3rm_robot/assets/panda_gripper_visual.obj
f3rm_robot/assets/tasks/caterpillar_ear.pt
f3rm_robot/assets/tasks/mug_handle.pt
f3rm_robot/assets/tasks/mug_lip.pt
f3rm_robot/assets/tasks/rack_place.pt
f3rm_robot/assets/tasks/screwdriver_handle.pt
f3rm_robot/examples/__init__.py
f3rm_robot/examples/generate_task.py
f3rm-0.0.6.dist-info/LICENSE
f3rm-0.0.6.dist-info/METADATA
f3rm-0.0.6.dist-info/WHEEL
f3rm-0.0.6.dist-info/entry_points.txt
f3rm-0.0.6.dist-info/top_level.txt
f3rm-0.0.6.dist-info/RECORD
