Metadata-Version: 2.1
Name: f3rm
Version: 0.0.6
Summary: F3RM: Feature Fields for Robotic Manipulation
Author-email: William Shen <willshen@csail.mit.edu>, Ge Yang <geyang@csail.mit.edu>
License: MIT License
Project-URL: Homepage, https://f3rm.csail.mit.edu
Project-URL: Source, https://github.com/f3rm/f3rm
Keywords: nerf,feature-fields,robotics
Classifier: License :: OSI Approved :: MIT License
Classifier: Programming Language :: Python :: 3
Requires-Python: >=3.8
License-File: LICENSE
Requires-Dist: einops
Requires-Dist: ftfy
Requires-Dist: gdown
Requires-Dist: matplotlib
Requires-Dist: nerfstudio >=0.3.3
Requires-Dist: numpy
Requires-Dist: pillow
Requires-Dist: regex
Requires-Dist: torchtyping
Requires-Dist: tqdm
Provides-Extra: dev
Requires-Dist: black ; extra == 'dev'
Requires-Dist: isort ; extra == 'dev'
Provides-Extra: robot
Requires-Dist: open3d ; extra == 'robot'
Requires-Dist: params-proto ; extra == 'robot'
Requires-Dist: PyMCubes ; extra == 'robot'
Requires-Dist: python-slugify ; extra == 'robot'
Requires-Dist: viser ; extra == 'robot'
